sixnine/__init__.py
sixnine/sxnn_class.py
six_nine-1.0.1.dist-info/LICENSE
six_nine-1.0.1.dist-info/METADATA
six_nine-1.0.1.dist-info/WHEEL
six_nine-1.0.1.dist-info/RECORD
