Metadata-Version: 2.1
Name: six-nine
Version: 1.0.1
Summary: Convenient and efficient library for obtaining 69 in various formats
License: GPL-3.0 license
Author: Adrian Makridenko
Author-email: adrian.makridenko@proton.me
Requires-Python: >=3.12,<4.0
Classifier: License :: Other/Proprietary License
Classifier: Programming Language :: Python :: 3
Classifier: Programming Language :: Python :: 3.12
